llama_index/README.md
llama_index/readers/minio/__init__.py
llama_index/readers/minio/boto3_client/__init__.py
llama_index/readers/minio/boto3_client/base.py
llama_index/readers/minio/minio_client/__init__.py
llama_index/readers/minio/minio_client/base.py
llama_index_readers_minio-0.4.1.dist-info/METADATA
llama_index_readers_minio-0.4.1.dist-info/WHEEL
llama_index_readers_minio-0.4.1.dist-info/licenses/LICENSE
llama_index_readers_minio-0.4.1.dist-info/RECORD
