Metadata-Version: 2.4
Name: llama-index-readers-minio
Version: 0.4.1
Summary: llama-index readers minio integration
Author-email: Your Name <you@example.com>
License-Expression: MIT
License-File: LICENSE
Requires-Python: <4.0,>=3.9
Requires-Dist: boto3<2,>=1.34.29
Requires-Dist: llama-index-core<0.15,>=0.13.0
Requires-Dist: minio<8,>=7.2.3
